{
  "companies": [
    {
      "company_id": "alpha_industrial",
      "dates": [
        {
          "date": "2025-01-01",
          "company_state": {
            "cash_runway_months": 13.0,
            "net_debt_to_ebitda": 2.4,
            "revenue_growth_pct": 3.5,
            "gross_margin_pct": 39.2,
            "transformation_pressure": "medium",
            "capacity_constraint": "low",
            "board_priority": "begin disciplined shift toward digital growth without impairing service quality"
          },
          "business_units": [
            {"unit_id": "core_legacy", "current_capex_share": 0.46, "roi_trend": "declining", "growth_outlook": "low", "execution_risk": "low", "absorptive_capacity": "low", "strategic_role": "cash_engine"},
            {"unit_id": "field_services", "current_capex_share": 0.22, "roi_trend": "stable", "growth_outlook": "medium", "execution_risk": "medium", "absorptive_capacity": "medium", "strategic_role": "customer_retention"},
            {"unit_id": "ai_platform", "current_capex_share": 0.14, "roi_trend": "emerging", "growth_outlook": "high", "execution_risk": "medium", "absorptive_capacity": "medium", "strategic_role": "future_growth"},
            {"unit_id": "cloud_services", "current_capex_share": 0.10, "roi_trend": "improving", "growth_outlook": "high", "execution_risk": "medium", "absorptive_capacity": "medium", "strategic_role": "future_growth"},
            {"unit_id": "field_automation", "current_capex_share": 0.08, "roi_trend": "emerging", "growth_outlook": "medium", "execution_risk": "high", "absorptive_capacity": "low", "strategic_role": "productivity_play"}
          ],
          "reallocation_constraints": {
            "reallocatable_share_cap": 0.48,
            "transfer_rules": [
              "At least 45% of any reduction from core_legacy must remain within industrial-adjacent units.",
              "Capital removed from regulated maintenance programs cannot be reassigned into speculative R&D in the same quarter."
            ],
            "unit_constraints": {
              "core_legacy": {"floor_share": 0.28, "ceiling_share": 0.52, "locked_share": 0.16},
              "field_services": {"floor_share": 0.14, "ceiling_share": 0.26, "locked_share": 0.04},
              "ai_platform": {"floor_share": 0.10, "ceiling_share": 0.34, "locked_share": 0.00},
              "cloud_services": {"floor_share": 0.08, "ceiling_share": 0.24, "locked_share": 0.00},
              "field_automation": {"floor_share": 0.05, "ceiling_share": 0.14, "locked_share": 0.00}
            }
          },
          "role_briefs": {
            "CFO": {
              "priority": "preserve balance-sheet resilience",
              "watch_for": ["cash risk", "debt pressure", "capital discipline"],
              "must_optimize": ["free_cash_flow_resilience", "downside_protection"],
              "veto_if": ["pro_forma_runway_below_10_months", "net_debt_to_ebitda_above_3_2x"]
            },
            "CTO": {
              "priority": "fund platform capability for future advantage",
              "watch_for": ["technical leverage", "innovation timing", "build feasibility"],
              "must_optimize": ["platform_compounding", "technical_option_value"],
              "veto_if": ["critical_platform_dependency_left_unfunded"]
            },
            "COO": {
              "priority": "avoid destabilizing operations",
              "watch_for": ["execution load", "transition risk", "delivery continuity"],
              "must_optimize": ["service_continuity", "transition_feasibility"],
              "veto_if": ["field_delivery_sla_breach_likely", "execution_load_exceeds_capacity"]
            },
            "CMO": {
              "priority": "capture market window",
              "watch_for": ["growth opportunity", "customer demand", "go-to-market timing"],
              "must_optimize": ["demand_capture", "share_gain_timing"],
              "veto_if": ["window_closes_within_two_quarters_if_underfunded"]
            }
          },
          "benchmark_context": {
            "mckinsey_reference": "Companies that reallocated more than 50% of capital expenditure across business units over ten years created about 50% more value.",
            "boldness_threshold": 0.50,
            "scenario_note": "Management has been incremental for years; board wants a credible but not reckless shift.",
            "boldness_is_desirable_if": ["balance_sheet_headroom_is_adequate", "receiving_units_have_positive_growth_conviction"],
            "boldness_is_undesirable_if": ["service_delivery_instability_rises", "destination_units_cannot_absorb_capital"]
          },
          "decision_history": [],
          "hidden_outcome_targets": {
            "preferred_min_share": 0.16,
            "preferred_max_share": 0.28,
            "preferred_receiving_units": ["ai_platform", "cloud_services"],
            "protected_units": ["field_services"],
            "overloaded_if_funded": ["field_automation"],
            "downside_if_too_conservative": "Transformation remains symbolic and growth option value decays.",
            "downside_if_too_aggressive": "Core reliability falls before digital units can absorb capital productively."
          }
        },
        {
          "date": "2025-04-01",
          "company_state": {
            "cash_runway_months": 11.0,
            "net_debt_to_ebitda": 2.8,
            "revenue_growth_pct": 4.2,
            "gross_margin_pct": 38.5,
            "transformation_pressure": "high",
            "capacity_constraint": "medium",
            "board_priority": "shift capital toward higher-growth units without breaking service continuity"
          },
          "business_units": [
            {"unit_id": "core_legacy", "current_capex_share": 0.42, "roi_trend": "declining", "growth_outlook": "low", "execution_risk": "low", "absorptive_capacity": "low", "strategic_role": "cash_engine"},
            {"unit_id": "field_services", "current_capex_share": 0.20, "roi_trend": "stable", "growth_outlook": "medium", "execution_risk": "medium", "absorptive_capacity": "medium", "strategic_role": "customer_retention"},
            {"unit_id": "ai_platform", "current_capex_share": 0.18, "roi_trend": "emerging", "growth_outlook": "high", "execution_risk": "medium", "absorptive_capacity": "high", "strategic_role": "future_growth"},
            {"unit_id": "cloud_services", "current_capex_share": 0.12, "roi_trend": "improving", "growth_outlook": "high", "execution_risk": "medium", "absorptive_capacity": "medium", "strategic_role": "future_growth"},
            {"unit_id": "field_automation", "current_capex_share": 0.08, "roi_trend": "emerging", "growth_outlook": "medium", "execution_risk": "high", "absorptive_capacity": "low", "strategic_role": "productivity_play"}
          ],
          "reallocation_constraints": {
            "reallocatable_share_cap": 0.62,
            "transfer_rules": [
              "At least 40% of any reduction from core_legacy must remain within industrial-adjacent units.",
              "Capital removed from regulated maintenance programs cannot be reassigned into speculative R&D in the same quarter."
            ],
            "unit_constraints": {
              "core_legacy": {"floor_share": 0.22, "ceiling_share": 0.50, "locked_share": 0.12},
              "field_services": {"floor_share": 0.12, "ceiling_share": 0.25, "locked_share": 0.03},
              "ai_platform": {"floor_share": 0.10, "ceiling_share": 0.45, "locked_share": 0.00},
              "cloud_services": {"floor_share": 0.08, "ceiling_share": 0.32, "locked_share": 0.00},
              "field_automation": {"floor_share": 0.05, "ceiling_share": 0.20, "locked_share": 0.00}
            }
          },
          "role_briefs": {
            "CFO": {
              "priority": "preserve balance-sheet resilience",
              "watch_for": ["cash risk", "debt pressure", "capital discipline"],
              "must_optimize": ["free_cash_flow_resilience", "downside_protection"],
              "veto_if": ["pro_forma_runway_below_9_months", "net_debt_to_ebitda_above_3_5x"]
            },
            "CTO": {
              "priority": "fund platform capability for future advantage",
              "watch_for": ["technical leverage", "innovation timing", "build feasibility"],
              "must_optimize": ["platform_compounding", "technical_option_value"],
              "veto_if": ["critical_platform_dependency_left_unfunded"]
            },
            "COO": {
              "priority": "avoid destabilizing operations",
              "watch_for": ["execution load", "transition risk", "delivery continuity"],
              "must_optimize": ["service_continuity", "transition_feasibility"],
              "veto_if": ["field_delivery_sla_breach_likely", "execution_load_exceeds_capacity"]
            },
            "CMO": {
              "priority": "capture market window",
              "watch_for": ["growth opportunity", "customer demand", "go-to-market timing"],
              "must_optimize": ["demand_capture", "share_gain_timing"],
              "veto_if": ["window_closes_within_two_quarters_if_underfunded"]
            }
          },
          "benchmark_context": {
            "mckinsey_reference": "Companies that reallocated more than 50% of capital expenditure across business units over ten years created about 50% more value.",
            "boldness_threshold": 0.50,
            "scenario_note": "Board patience is thinner; under-reallocation is now also a risk.",
            "boldness_is_desirable_if": ["balance_sheet_headroom_is_adequate", "receiving_units_have_positive_growth_conviction", "execution_disruption_risk_is_contained"],
            "boldness_is_undesirable_if": ["liquidity_is_fragile", "reallocated_capital_overloads_operations", "destination_units_cannot_absorb_capital_productively"]
          },
          "decision_history": [
            {
              "date": "2025-01-01",
              "allocation_plan": {
                "from_units": {"core_legacy": -0.10},
                "to_units": {"ai_platform": 0.06, "cloud_services": 0.04}
              },
              "decision_type": "moderate",
              "reallocation_share": 0.10,
              "ceo_rationale": "Initiated a measured shift while preserving industrial reliability."
            }
          ],
          "hidden_outcome_targets": {
            "preferred_min_share": 0.22,
            "preferred_max_share": 0.34,
            "preferred_receiving_units": ["ai_platform", "cloud_services"],
            "protected_units": ["field_services"],
            "overloaded_if_funded": ["field_automation"],
            "downside_if_too_conservative": "Growth window is missed and investors continue discounting the transformation story.",
            "downside_if_too_aggressive": "Execution strain causes service gaps before the new units can monetize."
          }
        },
        {
          "date": "2025-07-01",
          "company_state": {
            "cash_runway_months": 8.7,
            "net_debt_to_ebitda": 3.3,
            "revenue_growth_pct": 3.9,
            "gross_margin_pct": 36.9,
            "transformation_pressure": "high",
            "capacity_constraint": "high",
            "board_priority": "continue the shift, but avoid a financing shock"
          },
          "business_units": [
            {"unit_id": "core_legacy", "current_capex_share": 0.37, "roi_trend": "declining", "growth_outlook": "low", "execution_risk": "medium", "absorptive_capacity": "low", "strategic_role": "cash_engine"},
            {"unit_id": "field_services", "current_capex_share": 0.21, "roi_trend": "stable", "growth_outlook": "medium", "execution_risk": "medium", "absorptive_capacity": "medium", "strategic_role": "customer_retention"},
            {"unit_id": "ai_platform", "current_capex_share": 0.21, "roi_trend": "emerging", "growth_outlook": "high", "execution_risk": "medium", "absorptive_capacity": "medium", "strategic_role": "future_growth"},
            {"unit_id": "cloud_services", "current_capex_share": 0.13, "roi_trend": "improving", "growth_outlook": "high", "execution_risk": "medium", "absorptive_capacity": "medium", "strategic_role": "future_growth"},
            {"unit_id": "field_automation", "current_capex_share": 0.08, "roi_trend": "emerging", "growth_outlook": "medium", "execution_risk": "high", "absorptive_capacity": "low", "strategic_role": "productivity_play"}
          ],
          "reallocation_constraints": {
            "reallocatable_share_cap": 0.38,
            "transfer_rules": [
              "At least 45% of any reduction from core_legacy must remain within industrial-adjacent units.",
              "Any plan increasing AI plus cloud by more than 0.12 must preserve field_services at or above 0.18."
            ],
            "unit_constraints": {
              "core_legacy": {"floor_share": 0.20, "ceiling_share": 0.46, "locked_share": 0.10},
              "field_services": {"floor_share": 0.18, "ceiling_share": 0.24, "locked_share": 0.05},
              "ai_platform": {"floor_share": 0.12, "ceiling_share": 0.42, "locked_share": 0.00},
              "cloud_services": {"floor_share": 0.10, "ceiling_share": 0.30, "locked_share": 0.00},
              "field_automation": {"floor_share": 0.05, "ceiling_share": 0.18, "locked_share": 0.00}
            }
          },
          "role_briefs": {
            "CFO": {
              "priority": "preserve financing flexibility",
              "watch_for": ["cash risk", "debt pressure", "capital discipline"],
              "must_optimize": ["runway_protection", "downside_protection"],
              "veto_if": ["pro_forma_runway_below_8_months", "net_debt_to_ebitda_above_3_6x"]
            },
            "CTO": {
              "priority": "avoid starving compounding digital platforms",
              "watch_for": ["technical leverage", "platform readiness", "build feasibility"],
              "must_optimize": ["platform_compounding", "delivery_of_core_roadmap"],
              "veto_if": ["critical_platform_dependency_left_unfunded"]
            },
            "COO": {
              "priority": "protect continuity under higher execution stress",
              "watch_for": ["execution load", "transition risk", "delivery continuity"],
              "must_optimize": ["service_continuity", "change_absorption"],
              "veto_if": ["field_delivery_sla_breach_likely", "execution_load_exceeds_capacity"]
            },
            "CMO": {
              "priority": "preserve visible market momentum",
              "watch_for": ["growth opportunity", "customer demand", "go-to-market timing"],
              "must_optimize": ["demand_capture", "share_gain_timing"],
              "veto_if": ["window_closes_within_two_quarters_if_underfunded"]
            }
          },
          "benchmark_context": {
            "mckinsey_reference": "Companies that reallocated more than 50% of capital expenditure across business units over ten years created about 50% more value.",
            "boldness_threshold": 0.50,
            "scenario_note": "The strategic need to shift remains real, but financial fragility has increased.",
            "boldness_is_desirable_if": ["market_window_is_still_open", "digital_units_can_absorb_capital", "financing_headroom_is_stable"],
            "boldness_is_undesirable_if": ["runway_is_fragile", "operational_continuity_is_at_risk", "reallocation_requires_external_financing"]
          },
          "decision_history": [
            {
              "date": "2025-01-01",
              "allocation_plan": {
                "from_units": {"core_legacy": -0.10},
                "to_units": {"ai_platform": 0.06, "cloud_services": 0.04}
              },
              "decision_type": "moderate",
              "reallocation_share": 0.10,
              "ceo_rationale": "Initiated a measured shift while preserving industrial reliability."
            },
            {
              "date": "2025-04-01",
              "allocation_plan": {
                "from_units": {"core_legacy": -0.15},
                "to_units": {"ai_platform": 0.10, "cloud_services": 0.05}
              },
              "decision_type": "conservative",
              "reallocation_share": 0.15,
              "ceo_rationale": "Preserved balance sheet while continuing the pivot."
            }
          ],
          "hidden_outcome_targets": {
            "preferred_min_share": 0.10,
            "preferred_max_share": 0.18,
            "preferred_receiving_units": ["ai_platform", "cloud_services"],
            "protected_units": ["field_services"],
            "overloaded_if_funded": ["field_automation", "ai_platform"],
            "downside_if_too_conservative": "The company looks indecisive and the transformation narrative weakens further.",
            "downside_if_too_aggressive": "Financing flexibility breaks and operations destabilize."
          }
        }
      ]
    },
    {
      "company_id": "nova_software",
      "dates": [
        {
          "date": "2025-02-01",
          "company_state": {
            "cash_runway_months": 18.0,
            "net_debt_to_ebitda": 1.1,
            "revenue_growth_pct": 9.4,
            "gross_margin_pct": 63.0,
            "transformation_pressure": "medium",
            "capacity_constraint": "medium",
            "board_priority": "accelerate enterprise AI monetization before the market window narrows"
          },
          "business_units": [
            {"unit_id": "core_smb", "current_capex_share": 0.30, "roi_trend": "stable", "growth_outlook": "medium", "execution_risk": "low", "absorptive_capacity": "low", "strategic_role": "cash_engine"},
            {"unit_id": "enterprise_ai", "current_capex_share": 0.20, "roi_trend": "emerging", "growth_outlook": "high", "execution_risk": "medium", "absorptive_capacity": "high", "strategic_role": "future_growth"},
            {"unit_id": "platform_reliability", "current_capex_share": 0.18, "roi_trend": "stable", "growth_outlook": "medium", "execution_risk": "low", "absorptive_capacity": "medium", "strategic_role": "customer_retention"},
            {"unit_id": "intl_gtm", "current_capex_share": 0.17, "roi_trend": "improving", "growth_outlook": "high", "execution_risk": "medium", "absorptive_capacity": "medium", "strategic_role": "growth_channel"},
            {"unit_id": "moonshots", "current_capex_share": 0.15, "roi_trend": "uncertain", "growth_outlook": "high", "execution_risk": "high", "absorptive_capacity": "low", "strategic_role": "optionality"}
          ],
          "reallocation_constraints": {
            "reallocatable_share_cap": 0.55,
            "transfer_rules": [
              "At least 0.14 of total share must remain allocated to platform_reliability.",
              "No more than 0.08 may be shifted into moonshots in a single planning period."
            ],
            "unit_constraints": {
              "core_smb": {"floor_share": 0.20, "ceiling_share": 0.35, "locked_share": 0.05},
              "enterprise_ai": {"floor_share": 0.14, "ceiling_share": 0.40, "locked_share": 0.00},
              "platform_reliability": {"floor_share": 0.14, "ceiling_share": 0.24, "locked_share": 0.08},
              "intl_gtm": {"floor_share": 0.10, "ceiling_share": 0.28, "locked_share": 0.00},
              "moonshots": {"floor_share": 0.05, "ceiling_share": 0.18, "locked_share": 0.00}
            }
          },
          "role_briefs": {
            "CFO": {
              "priority": "preserve efficiency despite strong balance sheet",
              "watch_for": ["capital discipline", "payback visibility", "portfolio sprawl"],
              "must_optimize": ["return_on_reallocated_capital", "cash_efficiency"],
              "veto_if": ["moonshots_expand_without_payback_case"]
            },
            "CTO": {
              "priority": "double down on platform-advantaged AI capabilities",
              "watch_for": ["technical leverage", "roadmap dependencies", "engineering absorption"],
              "must_optimize": ["model_product_synergy", "platform_compounding"],
              "veto_if": ["enterprise_ai_underfunded_relative_to_committed_roadmap"]
            },
            "COO": {
              "priority": "protect reliability while scaling",
              "watch_for": ["incident risk", "ops staffing load", "release complexity"],
              "must_optimize": ["service_continuity", "operational_readiness"],
              "veto_if": ["platform_reliability_drops_below_safe_floor"]
            },
            "CMO": {
              "priority": "capture enterprise adoption while momentum is favorable",
              "watch_for": ["win_rate", "pipeline conversion", "regional timing"],
              "must_optimize": ["demand_capture", "distribution_scale"],
              "veto_if": ["intl_gtm_remains_underfunded_for_live_pipeline"]
            }
          },
          "benchmark_context": {
            "mckinsey_reference": "Companies that reallocated more than 50% of capital expenditure across business units over ten years created about 50% more value.",
            "boldness_threshold": 0.50,
            "scenario_note": "Nova has the headroom to be bold; the bigger mistake may be being too timid.",
            "boldness_is_desirable_if": ["balance_sheet_headroom_is_strong", "enterprise_ai_and_intl_gtm_can_absorb_capital"],
            "boldness_is_undesirable_if": ["platform_reliability_is_starved", "too_much_goes_into_moonshots"]
          },
          "decision_history": [],
          "hidden_outcome_targets": {
            "preferred_min_share": 0.24,
            "preferred_max_share": 0.38,
            "preferred_receiving_units": ["enterprise_ai", "intl_gtm"],
            "protected_units": ["platform_reliability"],
            "overloaded_if_funded": ["moonshots"],
            "downside_if_too_conservative": "Enterprise AI monetization window is underexploited and competitors catch up.",
            "downside_if_too_aggressive": "Reliability and execution quality erode, hurting retention."
          }
        },
        {
          "date": "2025-05-01",
          "company_state": {
            "cash_runway_months": 15.5,
            "net_debt_to_ebitda": 1.4,
            "revenue_growth_pct": 10.1,
            "gross_margin_pct": 61.8,
            "transformation_pressure": "high",
            "capacity_constraint": "medium",
            "board_priority": "lean into enterprise AI while maintaining reliability discipline"
          },
          "business_units": [
            {"unit_id": "core_smb", "current_capex_share": 0.27, "roi_trend": "stable", "growth_outlook": "medium", "execution_risk": "low", "absorptive_capacity": "low", "strategic_role": "cash_engine"},
            {"unit_id": "enterprise_ai", "current_capex_share": 0.24, "roi_trend": "improving", "growth_outlook": "high", "execution_risk": "medium", "absorptive_capacity": "high", "strategic_role": "future_growth"},
            {"unit_id": "platform_reliability", "current_capex_share": 0.17, "roi_trend": "stable", "growth_outlook": "medium", "execution_risk": "low", "absorptive_capacity": "medium", "strategic_role": "customer_retention"},
            {"unit_id": "intl_gtm", "current_capex_share": 0.18, "roi_trend": "improving", "growth_outlook": "high", "execution_risk": "medium", "absorptive_capacity": "high", "strategic_role": "growth_channel"},
            {"unit_id": "moonshots", "current_capex_share": 0.14, "roi_trend": "uncertain", "growth_outlook": "medium", "execution_risk": "high", "absorptive_capacity": "low", "strategic_role": "optionality"}
          ],
          "reallocation_constraints": {
            "reallocatable_share_cap": 0.52,
            "transfer_rules": [
              "At least 0.15 of total share must remain allocated to platform_reliability.",
              "No more than 0.06 may be shifted into moonshots in a single planning period."
            ],
            "unit_constraints": {
              "core_smb": {"floor_share": 0.18, "ceiling_share": 0.32, "locked_share": 0.04},
              "enterprise_ai": {"floor_share": 0.18, "ceiling_share": 0.42, "locked_share": 0.00},
              "platform_reliability": {"floor_share": 0.15, "ceiling_share": 0.23, "locked_share": 0.08},
              "intl_gtm": {"floor_share": 0.12, "ceiling_share": 0.30, "locked_share": 0.00},
              "moonshots": {"floor_share": 0.04, "ceiling_share": 0.16, "locked_share": 0.00}
            }
          },
          "role_briefs": {
            "CFO": {
              "priority": "maintain efficient growth, not just growth",
              "watch_for": ["payback visibility", "portfolio sprawl", "operating leverage"],
              "must_optimize": ["return_on_reallocated_capital", "cash_efficiency"],
              "veto_if": ["moonshots_expand_without_payback_case"]
            },
            "CTO": {
              "priority": "keep compounding the enterprise AI lead",
              "watch_for": ["technical leverage", "roadmap dependencies", "engineering absorption"],
              "must_optimize": ["model_product_synergy", "platform_compounding"],
              "veto_if": ["enterprise_ai_underfunded_relative_to_committed_roadmap"]
            },
            "COO": {
              "priority": "protect reliability while scaling enterprise customers",
              "watch_for": ["incident risk", "ops staffing load", "release complexity"],
              "must_optimize": ["service_continuity", "operational_readiness"],
              "veto_if": ["platform_reliability_drops_below_safe_floor"]
            },
            "CMO": {
              "priority": "push into enterprise accounts and international demand",
              "watch_for": ["win_rate", "pipeline conversion", "regional timing"],
              "must_optimize": ["demand_capture", "distribution_scale"],
              "veto_if": ["intl_gtm_remains_underfunded_for_live_pipeline"]
            }
          },
          "benchmark_context": {
            "mckinsey_reference": "Companies that reallocated more than 50% of capital expenditure across business units over ten years created about 50% more value.",
            "boldness_threshold": 0.50,
            "scenario_note": "Nova can still be bold, but reliability is now the main balancing constraint.",
            "boldness_is_desirable_if": ["enterprise_demand_is_real", "engineering_can_absorb_the_shift"],
            "boldness_is_undesirable_if": ["platform_reliability_is_squeezed", "too_much_capital_leaks_into_low-payback_bets"]
          },
          "decision_history": [
            {
              "date": "2025-02-01",
              "allocation_plan": {
                "from_units": {"core_smb": -0.10},
                "to_units": {"enterprise_ai": 0.06, "intl_gtm": 0.04}
              },
              "decision_type": "moderate",
              "reallocation_share": 0.10,
              "ceo_rationale": "Started shifting toward AI monetization while preserving reliability."
            }
          ],
          "hidden_outcome_targets": {
            "preferred_min_share": 0.18,
            "preferred_max_share": 0.30,
            "preferred_receiving_units": ["enterprise_ai", "intl_gtm"],
            "protected_units": ["platform_reliability"],
            "overloaded_if_funded": ["moonshots"],
            "downside_if_too_conservative": "Enterprise momentum slows and channel expansion is underfunded.",
            "downside_if_too_aggressive": "Reliability erosion hurts customer trust and renewal."
          }
        }
      ]
    }
  ]
}
